GetProxyIp/GetProxyIp.py
GetProxyIp/__init__.py
GetProxyIp-0.0.1.dist-info/LICENSE
GetProxyIp-0.0.1.dist-info/METADATA
GetProxyIp-0.0.1.dist-info/WHEEL
GetProxyIp-0.0.1.dist-info/top_level.txt
GetProxyIp-0.0.1.dist-info/RECORD
